[
  {
    "date": "2019-09-01",
    "Rain": 57.7,
    "AQI": 49.0
  },
  {
    "date": "2019-09-02",
    "Rain": 31.2,
    "AQI": 34.0
  },
  {
    "date": "2019-09-03",
    "Rain": 3.7,
    "AQI": 35.0
  },
  {
    "date": "2019-09-04",
    "Rain": 19.9,
    "AQI": 35.0
  },
  {
    "date": "2019-09-05",
    "Rain": 38.3,
    "AQI": 40.0
  },
  {
    "date": "2019-09-06",
    "Rain": 0.4,
    "AQI": 43.0
  },
  {
    "date": "2019-09-07",
    "Rain": 0.0,
    "AQI": 56.0
  },
  {
    "date": "2019-09-08",
    "Rain": 1.7,
    "AQI": 65.0
  },
  {
    "date": "2019-09-09",
    "Rain": 28.6,
    "AQI": 63.0
  },
  {
    "date": "2019-09-10",
    "Rain": 3.0,
    "AQI": 51.0
  },
  {
    "date": "2019-09-11",
    "Rain": 0.0,
    "AQI": 42.0
  },
  {
    "date": "2019-09-12",
    "Rain": 0.0,
    "AQI": 51.0
  },
  {
    "date": "2019-09-13",
    "Rain": 0.0,
    "AQI": 56.0
  },
  {
    "date": "2019-09-14",
    "Rain": 13.6,
    "AQI": 62.0
  },
  {
    "date": "2019-09-15",
    "Rain": 5.3,
    "AQI": 62.0
  },
  {
    "date": "2019-09-16",
    "Rain": 15.0,
    "AQI": 58.0
  },
  {
    "date": "2019-09-17",
    "Rain": 0.0,
    "AQI": 53.0
  },
  {
    "date": "2019-09-18",
    "Rain": 0.0,
    "AQI": 56.0
  },
  {
    "date": "2019-09-19",
    "Rain": 0.0,
    "AQI": 56.0
  },
  {
    "date": "2019-09-20",
    "Rain": 0.0,
    "AQI": 55.0
  },
  {
    "date": "2019-09-21",
    "Rain": 0.0,
    "AQI": 48.0
  },
  {
    "date": "2019-09-22",
    "Rain": 0.0,
    "AQI": 45.0
  },
  {
    "date": "2019-09-23",
    "Rain": 0.0,
    "AQI": 47.0
  },
  {
    "date": "2019-09-24",
    "Rain": 0.0,
    "AQI": 61.0
  },
  {
    "date": "2019-09-25",
    "Rain": 0.0,
    "AQI": 59.0
  },
  {
    "date": "2019-09-26",
    "Rain": 0.0,
    "AQI": 77.0
  },
  {
    "date": "2019-09-27",
    "Rain": 0.0,
    "AQI": 69.0
  },
  {
    "date": "2019-09-28",
    "Rain": 0.0,
    "AQI": 63.0
  },
  {
    "date": "2019-09-29",
    "Rain": 0.0,
    "AQI": 73.0
  },
  {
    "date": "2019-09-30",
    "Rain": 0.0,
    "AQI": 82.0
  },
  {
    "date": "2019-10-01",
    "Rain": 0.0,
    "AQI": 79.0
  },
  {
    "date": "2019-10-02",
    "Rain": 0.0,
    "AQI": 69.0
  },
  {
    "date": "2019-10-03",
    "Rain": 0.0,
    "AQI": 72.0
  },
  {
    "date": "2019-10-04",
    "Rain": 0.0,
    "AQI": 66.0
  },
  {
    "date": "2019-10-05",
    "Rain": 7.6,
    "AQI": 63.0
  },
  {
    "date": "2019-10-06",
    "Rain": 9.9,
    "AQI": 61.0
  },
  {
    "date": "2019-10-07",
    "Rain": 15.2,
    "AQI": 68.0
  },
  {
    "date": "2019-10-08",
    "Rain": 0.0,
    "AQI": 66.0
  },
  {
    "date": "2019-10-09",
    "Rain": 0.0,
    "AQI": 57.0
  },
  {
    "date": "2019-10-10",
    "Rain": 0.0,
    "AQI": 69.0
  },
  {
    "date": "2019-10-11",
    "Rain": 23.4,
    "AQI": 77.0
  },
  {
    "date": "2019-10-12",
    "Rain": 10.2,
    "AQI": 66.0
  },
  {
    "date": "2019-10-13",
    "Rain": 0.0,
    "AQI": 58.0
  },
  {
    "date": "2019-10-14",
    "Rain": 1.4,
    "AQI": 59.0
  },
  {
    "date": "2019-10-15",
    "Rain": 3.7,
    "AQI": 44.0
  },
  {
    "date": "2019-10-16",
    "Rain": 0.0,
    "AQI": 49.0
  },
  {
    "date": "2019-10-17",
    "Rain": 0.0,
    "AQI": 51.0
  },
  {
    "date": "2019-10-18",
    "Rain": 0.0,
    "AQI": 49.0
  },
  {
    "date": "2019-10-19",
    "Rain": 0.0,
    "AQI": 54.0
  },
  {
    "date": "2019-10-20",
    "Rain": 0.0,
    "AQI": 58.0
  },
  {
    "date": "2019-10-21",
    "Rain": 0.0,
    "AQI": 66.0
  },
  {
    "date": "2019-10-22",
    "Rain": 0.0,
    "AQI": 76.0
  },
  {
    "date": "2019-10-23",
    "Rain": 7.9,
    "AQI": 72.0
  },
  {
    "date": "2019-10-24",
    "Rain": 0.0,
    "AQI": 73.0
  },
  {
    "date": "2019-10-25",
    "Rain": 1.6,
    "AQI": 79.0
  },
  {
    "date": "2019-10-26",
    "Rain": 0.0,
    "AQI": 30.0
  },
  {
    "date": "2019-10-27",
    "Rain": 0.6,
    "AQI": 39.0
  },
  {
    "date": "2019-10-28",
    "Rain": 13.2,
    "AQI": 33.0
  },
  {
    "date": "2019-10-29",
    "Rain": 0.0,
    "AQI": 44.0
  },
  {
    "date": "2019-10-30",
    "Rain": 0.0,
    "AQI": 69.0
  },
  {
    "date": "2019-10-31",
    "Rain": 0.0,
    "AQI": 78.0
  },
  {
    "date": "2019-11-01",
    "Rain": 0.0,
    "AQI": 75.0
  },
  {
    "date": "2019-11-02",
    "Rain": 0.0,
    "AQI": 71.0
  },
  {
    "date": "2019-11-03",
    "Rain": 0.0,
    "AQI": 70.0
  },
  {
    "date": "2019-11-04",
    "Rain": 0.0,
    "AQI": 74.0
  },
  {
    "date": "2019-11-05",
    "Rain": 0.0,
    "AQI": 60.0
  },
  {
    "date": "2019-11-06",
    "Rain": 0.0,
    "AQI": 61.0
  },
  {
    "date": "2019-11-07",
    "Rain": 0.0,
    "AQI": 62.0
  },
  {
    "date": "2019-11-08",
    "Rain": 0.0,
    "AQI": 57.0
  },
  {
    "date": "2019-11-09",
    "Rain": 0.0,
    "AQI": 58.0
  },
  {
    "date": "2019-11-10",
    "Rain": 0.0,
    "AQI": 68.0
  },
  {
    "date": "2019-11-11",
    "Rain": 0.0,
    "AQI": 81.0
  },
  {
    "date": "2019-11-12",
    "Rain": 0.0,
    "AQI": 79.0
  },
  {
    "date": "2019-11-13",
    "Rain": 0.0,
    "AQI": 72.0
  },
  {
    "date": "2019-11-14",
    "Rain": 0.0,
    "AQI": 52.0
  },
  {
    "date": "2019-11-15",
    "Rain": 0.0,
    "AQI": 70.0
  },
  {
    "date": "2019-11-16",
    "Rain": 0.0,
    "AQI": 79.0
  },
  {
    "date": "2019-11-17",
    "Rain": 5.9,
    "AQI": 78.0
  },
  {
    "date": "2019-11-18",
    "Rain": 4.0,
    "AQI": 52.0
  },
  {
    "date": "2019-11-19",
    "Rain": 0.0,
    "AQI": 46.0
  },
  {
    "date": "2019-11-20",
    "Rain": 0.0,
    "AQI": 59.0
  },
  {
    "date": "2019-11-21",
    "Rain": 0.0,
    "AQI": 63.0
  },
  {
    "date": "2019-11-22",
    "Rain": 0.0,
    "AQI": 74.0
  },
  {
    "date": "2019-11-23",
    "Rain": 0.0,
    "AQI": 88.0
  },
  {
    "date": "2019-11-24",
    "Rain": 0.0,
    "AQI": 81.0
  },
  {
    "date": "2019-11-25",
    "Rain": 0.0,
    "AQI": 69.0
  },
  {
    "date": "2019-11-26",
    "Rain": 0.0,
    "AQI": 35.0
  },
  {
    "date": "2019-11-27",
    "Rain": 0.0,
    "AQI": 27.0
  },
  {
    "date": "2019-11-28",
    "Rain": 0.0,
    "AQI": 20.0
  },
  {
    "date": "2019-11-29",
    "Rain": 0.0,
    "AQI": 33.0
  },
  {
    "date": "2019-11-30",
    "Rain": 0.0,
    "AQI": 46.0
  },
  {
    "date": "2019-12-01",
    "Rain": 0.0,
    "AQI": 47.0
  },
  {
    "date": "2019-12-02",
    "Rain": 0.0,
    "AQI": 42.0
  },
  {
    "date": "2019-12-03",
    "Rain": 0.0,
    "AQI": 60.0
  },
  {
    "date": "2019-12-04",
    "Rain": 0.0,
    "AQI": 62.0
  },
  {
    "date": "2019-12-05",
    "Rain": 0.0,
    "AQI": 55.0
  },
  {
    "date": "2019-12-06",
    "Rain": 0.0,
    "AQI": 57.0
  },
  {
    "date": "2019-12-07",
    "Rain": 0.0,
    "AQI": 59.0
  },
  {
    "date": "2019-12-08",
    "Rain": 0.0,
    "AQI": 58.0
  },
  {
    "date": "2019-12-09",
    "Rain": 0.0,
    "AQI": 73.0
  },
  {
    "date": "2019-12-10",
    "Rain": 0.0,
    "AQI": 85.0
  },
  {
    "date": "2019-12-11",
    "Rain": 0.0,
    "AQI": 75.0
  },
  {
    "date": "2019-12-12",
    "Rain": 0.0,
    "AQI": 82.0
  },
  {
    "date": "2019-12-13",
    "Rain": 0.0,
    "AQI": 82.0
  },
  {
    "date": "2019-12-14",
    "Rain": 0.0,
    "AQI": 91.0
  },
  {
    "date": "2019-12-15",
    "Rain": 0.0,
    "AQI": 74.0
  },
  {
    "date": "2019-12-16",
    "Rain": 0.0,
    "AQI": 41.0
  },
  {
    "date": "2019-12-17",
    "Rain": 1.1,
    "AQI": 54.0
  },
  {
    "date": "2019-12-18",
    "Rain": 10.5,
    "AQI": 85.0
  },
  {
    "date": "2019-12-19",
    "Rain": 19.5,
    "AQI": 20.0
  },
  {
    "date": "2019-12-20",
    "Rain": 0.6,
    "AQI": 21.0
  },
  {
    "date": "2019-12-21",
    "Rain": 31.5,
    "AQI": 18.0
  },
  {
    "date": "2019-12-22",
    "Rain": 1.3,
    "AQI": 16.0
  },
  {
    "date": "2019-12-23",
    "Rain": 1.8,
    "AQI": 37.0
  },
  {
    "date": "2019-12-24",
    "Rain": 0.0,
    "AQI": 26.0
  },
  {
    "date": "2019-12-25",
    "Rain": 0.7,
    "AQI": 51.0
  },
  {
    "date": "2019-12-26",
    "Rain": 2.0,
    "AQI": 32.0
  },
  {
    "date": "2019-12-27",
    "Rain": 0.0,
    "AQI": 46.0
  },
  {
    "date": "2019-12-28",
    "Rain": 0.0,
    "AQI": 71.0
  },
  {
    "date": "2019-12-29",
    "Rain": 0.0,
    "AQI": 74.0
  },
  {
    "date": "2019-12-30",
    "Rain": 0.6,
    "AQI": 72.0
  },
  {
    "date": "2019-12-31",
    "Rain": 1.8,
    "AQI": 72.0
  },
  {
    "date": "2020-01-01",
    "Rain": 0.0,
    "AQI": 72.0
  },
  {
    "date": "2020-01-02",
    "Rain": 0.0,
    "AQI": 76.0
  },
  {
    "date": "2020-01-03",
    "Rain": 0.0,
    "AQI": 75.0
  },
  {
    "date": "2020-01-04",
    "Rain": 0.0,
    "AQI": 80.0
  },
  {
    "date": "2020-01-05",
    "Rain": 0.0,
    "AQI": 78.0
  },
  {
    "date": "2020-01-06",
    "Rain": 0.0,
    "AQI": 45.0
  },
  {
    "date": "2020-01-07",
    "Rain": 0.0,
    "AQI": 39.0
  },
  {
    "date": "2020-01-08",
    "Rain": 0.0,
    "AQI": 35.0
  },
  {
    "date": "2020-01-09",
    "Rain": 0.0,
    "AQI": 61.0
  },
  {
    "date": "2020-01-10",
    "Rain": 0.1,
    "AQI": 78.0
  },
  {
    "date": "2020-01-11",
    "Rain": 8.9,
    "AQI": 29.0
  },
  {
    "date": "2020-01-12",
    "Rain": 0.0,
    "AQI": 23.0
  },
  {
    "date": "2020-01-13",
    "Rain": 0.3,
    "AQI": 39.0
  },
  {
    "date": "2020-01-14",
    "Rain": 9.3,
    "AQI": 40.0
  },
  {
    "date": "2020-01-15",
    "Rain": 9.8,
    "AQI": 50.0
  },
  {
    "date": "2020-01-16",
    "Rain": 12.2,
    "AQI": 20.0
  },
  {
    "date": "2020-01-17",
    "Rain": 0.0,
    "AQI": 21.0
  },
  {
    "date": "2020-01-18",
    "Rain": 0.0,
    "AQI": 41.0
  },
  {
    "date": "2020-01-19",
    "Rain": 0.0,
    "AQI": 42.0
  },
  {
    "date": "2020-01-20",
    "Rain": 0.0,
    "AQI": 42.0
  },
  {
    "date": "2020-01-21",
    "Rain": 0.0,
    "AQI": 45.0
  },
  {
    "date": "2020-01-22",
    "Rain": 0.0,
    "AQI": 38.0
  },
  {
    "date": "2020-01-23",
    "Rain": 15.4,
    "AQI": 59.0
  },
  {
    "date": "2020-01-24",
    "Rain": 21.4,
    "AQI": 21.0
  },
  {
    "date": "2020-01-25",
    "Rain": 125.3,
    "AQI": 15.0
  },
  {
    "date": "2020-01-26",
    "Rain": 21.5,
    "AQI": 15.0
  },
  {
    "date": "2020-01-27",
    "Rain": 0.9,
    "AQI": 19.0
  },
  {
    "date": "2020-01-28",
    "Rain": 0.0,
    "AQI": 27.0
  },
  {
    "date": "2020-01-29",
    "Rain": 0.0,
    "AQI": 35.0
  },
  {
    "date": "2020-01-30",
    "Rain": 0.0,
    "AQI": 41.0
  },
  {
    "date": "2020-01-31",
    "Rain": 0.0,
    "AQI": 42.0
  },
  {
    "date": "2020-02-01",
    "Rain": 0.0,
    "AQI": 44.0
  },
  {
    "date": "2020-02-02",
    "Rain": 19.0,
    "AQI": 44.0
  },
  {
    "date": "2020-02-03",
    "Rain": 59.2,
    "AQI": 30.0
  },
  {
    "date": "2020-02-04",
    "Rain": 41.7,
    "AQI": 36.0
  },
  {
    "date": "2020-02-05",
    "Rain": 2.1,
    "AQI": 37.0
  },
  {
    "date": "2020-02-06",
    "Rain": 54.3,
    "AQI": 32.0
  },
  {
    "date": "2020-02-07",
    "Rain": 1.5,
    "AQI": 20.0
  },
  {
    "date": "2020-02-08",
    "Rain": 0.7,
    "AQI": 23.0
  },
  {
    "date": "2020-02-09",
    "Rain": 0.8,
    "AQI": 30.0
  },
  {
    "date": "2020-02-10",
    "Rain": 0.0,
    "AQI": 28.0
  },
  {
    "date": "2020-02-11",
    "Rain": 9.0,
    "AQI": 30.0
  },
  {
    "date": "2020-02-12",
    "Rain": 64.9,
    "AQI": 22.0
  },
  {
    "date": "2020-02-13",
    "Rain": 138.1,
    "AQI": 21.0
  },
  {
    "date": "2020-02-14",
    "Rain": 74.9,
    "AQI": 18.0
  },
  {
    "date": "2020-02-15",
    "Rain": 231.1,
    "AQI": 14.0
  },
  {
    "date": "2020-02-16",
    "Rain": 0.2,
    "AQI": 20.0
  },
  {
    "date": "2020-02-17",
    "Rain": 0.0,
    "AQI": 26.0
  },
  {
    "date": "2020-02-18",
    "Rain": 0.0,
    "AQI": 28.0
  },
  {
    "date": "2020-02-19",
    "Rain": 0.0,
    "AQI": 32.0
  },
  {
    "date": "2020-02-20",
    "Rain": 0.0,
    "AQI": 46.0
  },
  {
    "date": "2020-02-21",
    "Rain": 0.0,
    "AQI": 50.0
  },
  {
    "date": "2020-02-22",
    "Rain": 0.0,
    "AQI": 51.0
  },
  {
    "date": "2020-02-23",
    "Rain": 0.0,
    "AQI": 53.0
  },
  {
    "date": "2020-02-24",
    "Rain": 0.3,
    "AQI": 54.0
  },
  {
    "date": "2020-02-25",
    "Rain": 0.0,
    "AQI": 42.0
  },
  {
    "date": "2020-02-26",
    "Rain": 0.5,
    "AQI": 50.0
  },
  {
    "date": "2020-02-27",
    "Rain": 0.3,
    "AQI": 48.0
  },
  {
    "date": "2020-02-28",
    "Rain": 0.0,
    "AQI": 33.0
  },
  {
    "date": "2020-02-29",
    "Rain": 46.7,
    "AQI": 37.0
  },
  {
    "date": "2020-03-01",
    "Rain": 3.0,
    "AQI": 30.0
  },
  {
    "date": "2020-03-02",
    "Rain": 2.9,
    "AQI": 30.0
  },
  {
    "date": "2020-03-03",
    "Rain": 42.7,
    "AQI": 25.0
  },
  {
    "date": "2020-03-04",
    "Rain": 85.8,
    "AQI": 19.0
  },
  {
    "date": "2020-03-05",
    "Rain": 0.0,
    "AQI": 29.0
  },
  {
    "date": "2020-03-06",
    "Rain": 3.4,
    "AQI": 34.0
  },
  {
    "date": "2020-03-07",
    "Rain": 53.3,
    "AQI": 33.0
  },
  {
    "date": "2020-03-08",
    "Rain": 23.3,
    "AQI": 33.0
  },
  {
    "date": "2020-03-09",
    "Rain": 52.9,
    "AQI": 25.0
  },
  {
    "date": "2020-03-10",
    "Rain": 0.3,
    "AQI": 33.0
  },
  {
    "date": "2020-03-11",
    "Rain": 12.3,
    "AQI": 49.0
  },
  {
    "date": "2020-03-12",
    "Rain": 46.1,
    "AQI": 33.0
  },
  {
    "date": "2020-03-13",
    "Rain": 18.5,
    "AQI": 19.0
  },
  {
    "date": "2020-03-14",
    "Rain": 0.0,
    "AQI": 49.0
  },
  {
    "date": "2020-03-15",
    "Rain": 0.0,
    "AQI": 61.0
  },
  {
    "date": "2020-03-16",
    "Rain": 1.9,
    "AQI": 66.0
  },
  {
    "date": "2020-03-17",
    "Rain": 30.3,
    "AQI": 45.0
  },
  {
    "date": "2020-03-18",
    "Rain": 59.2,
    "AQI": 39.0
  },
  {
    "date": "2020-03-19",
    "Rain": 10.9,
    "AQI": 35.0
  },
  {
    "date": "2020-03-20",
    "Rain": 3.7,
    "AQI": 37.0
  },
  {
    "date": "2020-03-21",
    "Rain": 0.3,
    "AQI": 26.0
  },
  {
    "date": "2020-03-22",
    "Rain": 20.6,
    "AQI": 37.0
  },
  {
    "date": "2020-03-23",
    "Rain": 15.3,
    "AQI": 33.0
  },
  {
    "date": "2020-03-24",
    "Rain": 100.6,
    "AQI": 39.0
  },
  {
    "date": "2020-03-25",
    "Rain": 5.1,
    "AQI": 47.0
  },
  {
    "date": "2020-03-26",
    "Rain": 14.2,
    "AQI": 41.0
  },
  {
    "date": "2020-03-27",
    "Rain": 91.6,
    "AQI": 37.0
  },
  {
    "date": "2020-03-28",
    "Rain": 0.6,
    "AQI": 20.0
  },
  {
    "date": "2020-03-29",
    "Rain": 32.7,
    "AQI": 21.0
  },
  {
    "date": "2020-03-30",
    "Rain": 23.9,
    "AQI": 13.0
  },
  {
    "date": "2020-03-31",
    "Rain": 23.2,
    "AQI": 16.0
  },
  {
    "date": "2020-04-01",
    "Rain": 4.0,
    "AQI": 23.0
  },
  {
    "date": "2020-04-02",
    "Rain": 78.3,
    "AQI": 25.0
  },
  {
    "date": "2020-04-03",
    "Rain": 181.8,
    "AQI": 14.0
  },
  {
    "date": "2020-04-04",
    "Rain": 39.5,
    "AQI": 35.0
  },
  {
    "date": "2020-04-05",
    "Rain": 27.7,
    "AQI": 55.0
  },
  {
    "date": "2020-04-06",
    "Rain": 3.2,
    "AQI": 47.0
  },
  {
    "date": "2020-04-07",
    "Rain": 0.0,
    "AQI": 51.0
  },
  {
    "date": "2020-04-08",
    "Rain": 0.3,
    "AQI": 65.0
  },
  {
    "date": "2020-04-09",
    "Rain": 0.0,
    "AQI": 68.0
  },
  {
    "date": "2020-04-10",
    "Rain": 15.0,
    "AQI": 74.0
  },
  {
    "date": "2020-04-11",
    "Rain": 60.7,
    "AQI": 42.0
  },
  {
    "date": "2020-04-12",
    "Rain": 0.0,
    "AQI": 30.0
  },
  {
    "date": "2020-04-13",
    "Rain": 0.0,
    "AQI": 47.0
  },
  {
    "date": "2020-04-14",
    "Rain": 0.0,
    "AQI": 60.0
  }
]
